{
	"configurations" : 
	[
		{
			"directories" : 
			[
				{
					"build" : ".",
					"jsonFile" : "directory-.-Debug-d0094a50bb2071803777.json",
					"minimumCMakeVersion" : 
					{
						"string" : "3.29"
					},
					"projectIndex" : 0,
					"source" : ".",
					"targetIndexes" : 
					[
						0
					]
				}
			],
			"name" : "Debug",
			"projects" : 
			[
				{
					"directoryIndexes" : 
					[
						0
					],
					"name" : "EPIC3_ASWD",
					"targetIndexes" : 
					[
						0
					]
				}
			],
			"targets" : 
			[
				{
					"directoryIndex" : 0,
					"id" : "EPIC3_ASWD::@6890427a1f51a3e7e1df",
					"jsonFile" : "target-EPIC3_ASWD-Debug-1d9d3f82382029578331.json",
					"name" : "EPIC3_ASWD",
					"projectIndex" : 0
				}
			]
		}
	],
	"kind" : "codemodel",
	"paths" : 
	{
		"build" : "C:/Users/Fernando/Desktop/Fernando/PrograIII (2)/EPIC3-ASWD/cmake-build-debug",
		"source" : "C:/Users/Fernando/Desktop/Fernando/PrograIII (2)/EPIC3-ASWD"
	},
	"version" : 
	{
		"major" : 2,
		"minor" : 7
	}
}
